gql_query_builder/__init__.py
gql_query_builder_with_pyproject-0.1.8.dist-info/LICENSE.txt
gql_query_builder_with_pyproject-0.1.8.dist-info/METADATA
gql_query_builder_with_pyproject-0.1.8.dist-info/WHEEL
gql_query_builder_with_pyproject-0.1.8.dist-info/top_level.txt
gql_query_builder_with_pyproject-0.1.8.dist-info/RECORD
