Metadata-Version: 2.1
Name: gql-query-builder-with-pyproject
Version: 0.1.8
Summary: This is a GraphQL query builder. This is a fork with pyproject to make installing easier
Author-email: youyo <1003ni2@gmail.com>
License: MIT License
Project-URL: Homepage, https://github.com/rtaycher/gql-query-builder
Keywords: graphql,gql,query-builder
Classifier: License :: OSI Approved :: MIT License
Classifier: Development Status :: 3 - Alpha
Classifier: Intended Audience :: Developers
Classifier: Topic :: Software Development
Classifier: License :: OSI Approved :: MIT License
Classifier: Programming Language :: Python :: 3
Requires-Python: >=3.6
License-File: LICENSE.txt
